noworkflow/__init__.py
noworkflow/__main__.py
noworkflow/now/__init__.py
noworkflow/now/cmd/__init__.py
noworkflow/now/cmd/cmd_dataflow.py
noworkflow/now/cmd/cmd_debug.py
noworkflow/now/cmd/cmd_demo.py
noworkflow/now/cmd/cmd_diff.py
noworkflow/now/cmd/cmd_export.py
noworkflow/now/cmd/cmd_helper.py
noworkflow/now/cmd/cmd_history.py
noworkflow/now/cmd/cmd_kernel.py
noworkflow/now/cmd/cmd_list.py
noworkflow/now/cmd/cmd_restore.py
noworkflow/now/cmd/cmd_run.py
noworkflow/now/cmd/cmd_schema.py
noworkflow/now/cmd/cmd_show.py
noworkflow/now/cmd/cmd_vis.py
noworkflow/now/cmd/command.py
noworkflow/now/collection/__init__.py
noworkflow/now/collection/helper.py
noworkflow/now/collection/metadata.py
noworkflow/now/collection/prov_definition/__init__.py
noworkflow/now/collection/prov_definition/ast_elements.py
noworkflow/now/collection/prov_definition/ast_helpers.py
noworkflow/now/collection/prov_definition/definition.py
noworkflow/now/collection/prov_definition/transformer.py
noworkflow/now/collection/prov_definition/transformer_expr.py
noworkflow/now/collection/prov_definition/transformer_stmt.py
noworkflow/now/collection/prov_deployment/__init__.py
noworkflow/now/collection/prov_deployment/deployment.py
noworkflow/now/collection/prov_deployment/py2module.py
noworkflow/now/collection/prov_deployment/py3module.py
noworkflow/now/collection/prov_execution/__init__.py
noworkflow/now/collection/prov_execution/collector.py
noworkflow/now/collection/prov_execution/debugger.py
noworkflow/now/collection/prov_execution/execution.py
noworkflow/now/collection/prov_execution/structures.py
noworkflow/now/ipython/__init__.py
noworkflow/now/ipython/converter.py
noworkflow/now/ipython/hierarchymagic.py
noworkflow/now/ipython/magics/__init__.py
noworkflow/now/ipython/magics/command.py
noworkflow/now/ipython/magics/now_ipython.py
noworkflow/now/ipython/magics/now_ls_magic.py
noworkflow/now/ipython/magics/now_prolog.py
noworkflow_alpha-2.0.0a0.dist-info/DESCRIPTION.rst
noworkflow_alpha-2.0.0a0.dist-info/METADATA
noworkflow_alpha-2.0.0a0.dist-info/RECORD
noworkflow_alpha-2.0.0a0.dist-info/WHEEL
noworkflow_alpha-2.0.0a0.dist-info/entry_points.txt
noworkflow_alpha-2.0.0a0.dist-info/metadata.json
noworkflow_alpha-2.0.0a0.dist-info/top_level.txt
